viprs-0.1.3.data/scripts/viprs_score
viprs-0.1.3.data/scripts/viprs_fit
viprs-0.1.3.data/scripts/viprs_evaluate
viprs/__init__.py
viprs/model/LDPredInf.py
viprs/model/VIPRSMix.py
viprs/model/__init__.py
viprs/model/VIPRS.py
viprs/model/BayesPRSModel.py
viprs/model/gridsearch/HyperparameterGrid.py
viprs/model/gridsearch/HyperparameterSearch.py
viprs/model/gridsearch/VIPRSGrid.py
viprs/model/gridsearch/grid_utils.py
viprs/model/gridsearch/__init__.py
viprs/model/vi/e_step_cpp.pxd
viprs/model/vi/__init__.py
viprs/model/vi/e_step_cpp.cpython-38-x86_64-linux-gnu.so
viprs/utils/exceptions.py
viprs/utils/OptimizeResult.py
viprs/utils/__init__.py
viprs/utils/math_utils.cpython-38-x86_64-linux-gnu.so
viprs/utils/compute_utils.py
viprs/utils/data_utils.py
viprs/utils/math_utils.pxd
viprs/plot/diagnostics.py
viprs/plot/__init__.py
viprs/eval/eval_utils.py
viprs/eval/continuous_metrics.py
viprs/eval/__init__.py
viprs/eval/binary_metrics.py
viprs/eval/pseudo_metrics.py
viprs.libs/libgomp-a34b3233.so.1.0.0
viprs-0.1.3.dist-info/LICENSE
viprs-0.1.3.dist-info/WHEEL
viprs-0.1.3.dist-info/RECORD
viprs-0.1.3.dist-info/top_level.txt
viprs-0.1.3.dist-info/METADATA
