Metadata-Version: 2.1
Name: viprs
Version: 0.1.3
Summary: Variational Inference of Polygenic Risk Scores (VIPRS)
Home-page: https://github.com/shz9/viprs
Author: Shadi Zabad
Author-email: shadi.zabad@mail.mcgill.ca
Classifier: Programming Language :: Python
Classifier: Intended Audience :: Developers
Classifier: Intended Audience :: Science/Research
Classifier: Topic :: Software Development :: Libraries :: Python Modules
Classifier: Topic :: Scientific/Engineering
Classifier: Operating System :: OS Independent
Classifier: Programming Language :: Python :: 3
Classifier: Programming Language :: Python :: 3.8
Classifier: Programming Language :: Python :: 3.9
Classifier: Programming Language :: Python :: 3.10
Classifier: Programming Language :: Python :: 3.11
Classifier: Programming Language :: Python :: 3.12
Requires-Python: >=3.8
License-File: LICENSE
Requires-Dist: numpy<2
Requires-Dist: scipy
Requires-Dist: pandas
Requires-Dist: tqdm
Requires-Dist: magenpy>=0.1.5
Requires-Dist: statsmodels
Requires-Dist: scikit-learn
Requires-Dist: psutil
Requires-Dist: joblib
Provides-Extra: docs
Requires-Dist: mkdocs; extra == "docs"
Requires-Dist: mkdocstrings-python; extra == "docs"
Requires-Dist: mkdocs-material; extra == "docs"
Requires-Dist: mkdocs-material-extensions; extra == "docs"
Provides-Extra: opt
Requires-Dist: scikit-optimize; extra == "opt"
Requires-Dist: seaborn; extra == "opt"
Provides-Extra: test
Requires-Dist: pytest; extra == "test"
